dcbroker/__init__.py
dcbroker/client.py
dcbroker-1.0.0.dist-info/licenses/LICENSE
dcbroker-1.0.0.dist-info/METADATA
dcbroker-1.0.0.dist-info/WHEEL
dcbroker-1.0.0.dist-info/top_level.txt
dcbroker-1.0.0.dist-info/RECORD
